eltetrado/__init__.py
eltetrado/analysis.py
eltetrado/cli.py
eltetrado/dto.py
eltetrado/example.fasta
eltetrado/h1.helix
eltetrado/h2.helix
eltetrado/model.py
eltetrado/quadraw.R
eltetrado-1.8.0.dist-info/METADATA
eltetrado-1.8.0.dist-info/WHEEL
eltetrado-1.8.0.dist-info/entry_points.txt
eltetrado-1.8.0.dist-info/licenses/LICENSE
eltetrado-1.8.0.dist-info/RECORD
