Metadata-Version: 2.4
Name: eltetrado
Version: 1.8.0
Summary: Find and classify tetrads and quadruplexes in DNA/RNA 3D structure
License: MIT
License-File: LICENSE
Keywords: bioinformatics,rna,dna,quadruplex,tetrad
Author: Tomasz Żok
Author-email: tomasz.zok@cs.put.poznan.pl
Requires-Python: >=3.12,<4.0
Classifier: Development Status :: 5 - Production/Stable
Classifier: Environment :: Console
Classifier: Intended Audience :: Science/Research
Classifier: License :: OSI Approved :: MIT License
Classifier: Operating System :: OS Independent
Classifier: Programming Language :: Python :: 3
Classifier: Programming Language :: Python :: 3.12
Classifier: Programming Language :: Python :: 3.13
Classifier: Programming Language :: Python :: 3.14
Classifier: Topic :: Scientific/Engineering :: Bio-Informatics
Requires-Dist: mmcif
Requires-Dist: numpy
Requires-Dist: orjson
Requires-Dist: rnapolis
Project-URL: Documentation, https://github.com/tzok/eltetrado
Project-URL: Homepage, https://github.com/tzok/eltetrado
Project-URL: Repository, https://github.com/tzok/eltetrado
